README.md
setup.py
dkmri/__init__.py
dkmri/asdki.py
dkmri/dkmri.py
dkmri/mlp.py
dkmri/msdki.py
dkmri.egg-info/PKG-INFO
dkmri.egg-info/SOURCES.txt
dkmri.egg-info/dependency_links.txt
dkmri.egg-info/requires.txt
dkmri.egg-info/top_level.txt