Metadata-Version: 2.1
Name: dkmri
Version: 0.0.4
Summary: Reproducible and efficient diffusion kurtosis imaging in Python.
Home-page: https://github.com/kerkelae/dkmri
Author: Leevi Kerkelä
Author-email: leevi.kerkela@protonmail.com
License: MIT
Platform: UNKNOWN
